README.md
setup.py
contributing/__init__.py
contributing/cli.py
contributing/fetch.py
contributing.egg-info/PKG-INFO
contributing.egg-info/SOURCES.txt
contributing.egg-info/dependency_links.txt
contributing.egg-info/entry_points.txt
contributing.egg-info/not-zip-safe
contributing.egg-info/requires.txt
contributing.egg-info/top_level.txt