Metadata-Version: 2.1
Name: contributing
Version: 1.0.0
Summary: Simple CONTRIBUTING.md generator.
Home-page: https://github.com/VoIlAlex/contributing
Author: voilalex
Author-email: ilya.vouk@gmail.com
License: MIT
Download-URL: https://github.com/VoIlAlex/contributing
Keywords: open source,cli,contributing,generator,markdown,license
Platform: UNKNOWN
Classifier: Programming Language :: Python :: 3.4
Classifier: Programming Language :: Python :: 3.5
Classifier: Programming Language :: Python :: 3.6
Classifier: Programming Language :: Python :: 3.7
Classifier: Programming Language :: Python :: 3.8
Classifier: License :: OSI Approved :: MIT License
Classifier: Topic :: Utilities
Classifier: Environment :: Console
Classifier: Intended Audience :: Developers
